gepa_rpc/adapter.py
gepa_rpc/cli.py
gepa_rpc/models.py
gepa_rpc/run.py
gepa_rpc-0.2.1.dist-info/METADATA
gepa_rpc-0.2.1.dist-info/WHEEL
gepa_rpc-0.2.1.dist-info/entry_points.txt
gepa_rpc-0.2.1.dist-info/licenses/LICENSE
gepa_rpc-0.2.1.dist-info/RECORD
