Metadata-Version: 2.4
Name: gepa-rpc
Version: 0.2.1
Summary: Run GEPA on your favorite non-python libraries.
License-File: LICENSE
Requires-Python: >=3.11
Requires-Dist: datasets>=4.4.2
Requires-Dist: dotenv>=0.9.9
Requires-Dist: fastapi>=0.115.0
Requires-Dist: gepa>=0.0.22
Requires-Dist: instructor>=1.13.0
Requires-Dist: litellm>=1.80.11
Requires-Dist: pydantic>=2.12.5
Requires-Dist: requests>=2.32.0
Requires-Dist: uvicorn>=0.30.0
